odoo/addons/account_promissory_note_deutschebank_es/README.rst
odoo/addons/account_promissory_note_deutschebank_es/__init__.py
odoo/addons/account_promissory_note_deutschebank_es/__manifest__.py
odoo/addons/account_promissory_note_deutschebank_es/data/account_promissory_note_report_data.xml
odoo/addons/account_promissory_note_deutschebank_es/i18n/account_promissory_note_deutschebank_es.pot
odoo/addons/account_promissory_note_deutschebank_es/i18n/ca.po
odoo/addons/account_promissory_note_deutschebank_es/i18n/es.po
odoo/addons/account_promissory_note_deutschebank_es/readme/CONFIGURE.rst
odoo/addons/account_promissory_note_deutschebank_es/readme/CONTRIBUTORS.rst
odoo/addons/account_promissory_note_deutschebank_es/readme/DESCRIPTION.rst
odoo/addons/account_promissory_note_deutschebank_es/readme/USAGE.rst
odoo/addons/account_promissory_note_deutschebank_es/report/__init__.py
odoo/addons/account_promissory_note_deutschebank_es/report/account_promissory_note_writing_report.xml
odoo/addons/account_promissory_note_deutschebank_es/report/check_print.py
odoo/addons/account_promissory_note_deutschebank_es/static/description/icon.png
odoo/addons/account_promissory_note_deutschebank_es/static/description/index.html
odoo/addons/account_promissory_note_deutschebank_es/views/report_promissory_note.xml
odoo12_addon_account_promissory_note_deutschebank_es-12.0.1.0.0.99.dev6.dist-info/METADATA
odoo12_addon_account_promissory_note_deutschebank_es-12.0.1.0.0.99.dev6.dist-info/WHEEL
odoo12_addon_account_promissory_note_deutschebank_es-12.0.1.0.0.99.dev6.dist-info/top_level.txt
odoo12_addon_account_promissory_note_deutschebank_es-12.0.1.0.0.99.dev6.dist-info/RECORD
